odoo/addons/ddmrp_exclude_moves_adu_calc/README.rst
odoo/addons/ddmrp_exclude_moves_adu_calc/__init__.py
odoo/addons/ddmrp_exclude_moves_adu_calc/__manifest__.py
odoo/addons/ddmrp_exclude_moves_adu_calc/i18n/ddmrp_exclude_moves_adu_calc.pot
odoo/addons/ddmrp_exclude_moves_adu_calc/i18n/fr.po
odoo/addons/ddmrp_exclude_moves_adu_calc/i18n/it.po
odoo/addons/ddmrp_exclude_moves_adu_calc/i18n/pt_BR.po
odoo/addons/ddmrp_exclude_moves_adu_calc/models/__init__.py
odoo/addons/ddmrp_exclude_moves_adu_calc/models/stock_buffer.py
odoo/addons/ddmrp_exclude_moves_adu_calc/models/stock_location.py
odoo/addons/ddmrp_exclude_moves_adu_calc/models/stock_move.py
odoo/addons/ddmrp_exclude_moves_adu_calc/readme/CONTRIBUTORS.rst
odoo/addons/ddmrp_exclude_moves_adu_calc/readme/CREDITS.rst
odoo/addons/ddmrp_exclude_moves_adu_calc/readme/DESCRIPTION.rst
odoo/addons/ddmrp_exclude_moves_adu_calc/readme/HISTORY.rst
odoo/addons/ddmrp_exclude_moves_adu_calc/readme/USAGE.rst
odoo/addons/ddmrp_exclude_moves_adu_calc/static/description/icon.png
odoo/addons/ddmrp_exclude_moves_adu_calc/static/description/index.html
odoo/addons/ddmrp_exclude_moves_adu_calc/tests/__init__.py
odoo/addons/ddmrp_exclude_moves_adu_calc/tests/test_ddmrp.py
odoo/addons/ddmrp_exclude_moves_adu_calc/views/stock_location_view.xml
odoo/addons/ddmrp_exclude_moves_adu_calc/views/stock_move_view.xml
odoo14_addon_ddmrp_exclude_moves_adu_calc-14.0.1.0.1.dist-info/METADATA
odoo14_addon_ddmrp_exclude_moves_adu_calc-14.0.1.0.1.dist-info/WHEEL
odoo14_addon_ddmrp_exclude_moves_adu_calc-14.0.1.0.1.dist-info/top_level.txt
odoo14_addon_ddmrp_exclude_moves_adu_calc-14.0.1.0.1.dist-info/RECORD
